qhchina/__init__.py
qhchina/config.py
qhchina/utils.py
qhchina/analytics/__init__.py
qhchina/analytics/collocations.py
qhchina/analytics/perplexity.py
qhchina/analytics/stylometry.py
qhchina/analytics/topicmodels.py
qhchina/analytics/vectors.py
qhchina/analytics/word2vec.py
qhchina/analytics/cython_ext/__init__.py
qhchina/analytics/cython_ext/collocations.cpp
qhchina/analytics/cython_ext/collocations.cpython-314-x86_64-linux-gnu.so
qhchina/analytics/cython_ext/collocations.pyx
qhchina/analytics/cython_ext/lda_sampler.cpython-314-x86_64-linux-gnu.so
qhchina/analytics/cython_ext/lda_sampler.pyx
qhchina/analytics/cython_ext/word2vec.cpython-314-x86_64-linux-gnu.so
qhchina/analytics/cython_ext/word2vec.pyx
qhchina/data/fonts/NotoSansTCSC-Regular.otf
qhchina/data/fonts/NotoSerifSC-Regular.otf
qhchina/data/fonts/NotoSerifTC-Regular.otf
qhchina/data/stopwords/zh_cl_sim.txt
qhchina/data/stopwords/zh_cl_tr.txt
qhchina/data/stopwords/zh_sim.txt
qhchina/data/stopwords/zh_tr.txt
qhchina/data/templates/document_visualization.html
qhchina/educational/__init__.py
qhchina/educational/llms.py
qhchina/educational/visuals.py
qhchina/helpers/__init__.py
qhchina/helpers/fonts.py
qhchina/helpers/texts.py
qhchina/preprocessing/__init__.py
qhchina/preprocessing/segmentation.py
qhchina-0.0.65.dist-info/METADATA
qhchina-0.0.65.dist-info/WHEEL
qhchina-0.0.65.dist-info/top_level.txt
qhchina-0.0.65.dist-info/RECORD
qhchina-0.0.65.dist-info/licenses/LICENSE
