Metadata-Version: 2.4
Name: qhchina
Version: 0.0.65
Summary: A Python package for NLP tasks related to Chinese text.
Author-email: Maciej Kurzynski <makurz@gmail.com>
License-Expression: MIT
Project-URL: Homepage, https://www.qhchina.org/pkg_docs
Project-URL: Documentation, https://www.qhchina.org/pkg_docs
Project-URL: Repository, https://github.com/mcjkurz/qhchina
Project-URL: Bug Tracker, https://github.com/mcjkurz/qhchina/issues
Keywords: digital humanities,nlp,Chinese,text analysis,corpus linguistics,topic modeling,stylometry
Classifier: Development Status :: 4 - Beta
Classifier: Intended Audience :: Science/Research
Classifier: Intended Audience :: Developers
Classifier: Operating System :: OS Independent
Classifier: Programming Language :: Python :: 3
Classifier: Programming Language :: Python :: 3.10
Classifier: Programming Language :: Python :: 3.11
Classifier: Programming Language :: Python :: 3.12
Classifier: Programming Language :: Python :: 3.13
Classifier: Programming Language :: Python :: 3.14
Classifier: Programming Language :: Cython
Classifier: Topic :: Text Processing :: Linguistic
Classifier: Topic :: Scientific/Engineering :: Artificial Intelligence
Classifier: Natural Language :: Chinese (Simplified)
Classifier: Natural Language :: Chinese (Traditional)
Requires-Python: >=3.10
License-File: LICENSE
Requires-Dist: numpy>=2.0.2
Requires-Dist: scipy>=1.14.1
Requires-Dist: matplotlib>=3.10.0
Requires-Dist: scikit-learn>=1.6.1
Requires-Dist: tqdm>=4.66.0
Requires-Dist: pandas>=2.1.0
Dynamic: license-file
